README.rst
setup.py
taio/__init__.py
taio/aio_core.c
taio/ctx_methods.c
taio/ctx_python.c
taio/file_methods.c
taio/file_python.c
taio/module_python.c
taio.egg-info/PKG-INFO
taio.egg-info/SOURCES.txt
taio.egg-info/dependency_links.txt
taio.egg-info/pbr.json
taio.egg-info/top_level.txt