Metadata-Version: 1.1
Name: taio
Version: 0.1
Summary: Twisted  Asynchronous I/O bindings (native linux)
Home-page: UNKNOWN
Author: Radoslaw Ryckowski
Author-email: radek.ryckowski@gmail.com
License: UNKNOWN
Platform: UNKNOWN
Classifier: Operating System :: POSIX
Classifier: Development Status :: 4 - Beta
Classifier: License :: OSI Approved :: BSD License
